jupyter_marvinjs/__init__.py
jupyter_marvinjs/_version.py
jupyter_marvinjs/marvin.py
jupyter_marvinjs/static/extension.js
jupyter_marvinjs/static/index.js
jupyter_marvinjs/static/index.js.map
jupyter_marvinjs-0.1.1.data/data/etc/jupyter/nbconfig/notebook.d/jupyter-marvinjs.json
jupyter_marvinjs-0.1.1.data/data/share/jupyter/nbextensions/jupyter-marvinjs/extension.js
jupyter_marvinjs-0.1.1.data/data/share/jupyter/nbextensions/jupyter-marvinjs/index.js
jupyter_marvinjs-0.1.1.data/data/share/jupyter/nbextensions/jupyter-marvinjs/index.js.map
jupyter_marvinjs-0.1.1.dist-info/METADATA
jupyter_marvinjs-0.1.1.dist-info/WHEEL
jupyter_marvinjs-0.1.1.dist-info/top_level.txt
jupyter_marvinjs-0.1.1.dist-info/RECORD
